CHANGES.txt
LICENSE.txt
MANIFEST.in
README.txt
setup.py
TabImport.egg-info/PKG-INFO
TabImport.egg-info/SOURCES.txt
TabImport.egg-info/dependency_links.txt
TabImport.egg-info/requires.txt
TabImport.egg-info/top_level.txt
tabimport/__init__.py
tabimport/forms.py
tabimport/urls.py
tabimport/views.py
tabimport/templates/tabimport/import.html