Metadata-Version: 1.0
Name: TabImport
Version: 0.3.4
Summary: Utility to ease reading data from tabular data files
Home-page: https://github.com/claudep/tabimport/
Author: Claude Paroz
Author-email: claude@2xlibre.net
License: LICENSE.txt
Platform: UNKNOWN
